esu/__init__.py
esu/backup.py
esu/base.py
esu/client.py
esu/disk.py
esu/dns.py
esu/dns_record.py
esu/firewall_template.py
esu/firewall_template_rule.py
esu/hypervisor.py
esu/image.py
esu/kubernetes.py
esu/kubernetes_template.py
esu/lbaas.py
esu/lbaas_pool.py
esu/manager.py
esu/network.py
esu/paas_service.py
esu/paas_template.py
esu/platform.py
esu/port.py
esu/port_forwarding.py
esu/port_forwarding_rule.py
esu/project.py
esu/public_key.py
esu/router.py
esu/router_firewall_rule.py
esu/router_port_forwarding.py
esu/router_route.py
esu/s3.py
esu/s3_bucket.py
esu/snapshot.py
esu/storage_profile.py
esu/subnet.py
esu/template.py
esu/template_field.py
esu/user.py
esu/vdc.py
esu/vm.py
esu/vm_metadata.py
rustack_esu-0.1.21.dist-info/LICENSE
rustack_esu-0.1.21.dist-info/METADATA
rustack_esu-0.1.21.dist-info/WHEEL
rustack_esu-0.1.21.dist-info/top_level.txt
rustack_esu-0.1.21.dist-info/RECORD
