Metadata-Version: 2.1
Name: rustack-esu
Version: 0.1.21
Summary: Rustack Cloud Platform API Wrapper
Home-page: https://github.com/rustack-cloud-platform/rcp-python
Author: Vladimir K Urushev
Author-email: urushev@yandex.ru
Maintainer: Vladimir K Urushev
Maintainer-email: urushev@yandex.ru
License: MIT
Download-URL: https://github.com/rustack-cloud-platform/rcp-python/tarball/0.1.21
Keywords: cloud,api
Platform: UNKNOWN
Classifier: Development Status :: 3 - Alpha
Classifier: Intended Audience :: Developers
Classifier: License :: OSI Approved :: MIT License
Classifier: Programming Language :: Python
Classifier: Programming Language :: Python :: 3
Classifier: Programming Language :: Python :: 3.5
Classifier: Programming Language :: Python :: 3.6
Classifier: Programming Language :: Python :: 3.7
Classifier: Programming Language :: Python :: 3.8
Classifier: Programming Language :: Python :: 3.9
Classifier: Programming Language :: Python :: 3.10
Classifier: Programming Language :: Python :: 3.11
Classifier: Programming Language :: Python :: 3 :: Only
Requires-Python: >=3.4
Requires-Dist: requests>=2.2.1
Provides-Extra: dev
Requires-Dist: responses; extra == "dev"
Requires-Dist: yapf==0.30.0; extra == "dev"
Requires-Dist: sphinx-rtd-theme==2.0.0; extra == "dev"
Requires-Dist: pylint; extra == "dev"
Requires-Dist: tox>=3.9.0; extra == "dev"
Requires-Dist: pytest>=4.6.2; extra == "dev"
Requires-Dist: pytest-cov>=2.7.1; extra == "dev"
Requires-Dist: tox-pyenv; platform_system == "darwin" and extra == "dev"
Requires-Dist: isort>=5.1.1; python_version >= "3.6" and extra == "dev"
